LICENSE
MANIFEST.in
README.rst
setup.py
bin/sitrep
sitrep/__init__.py
sitrep/core.py
sitrep.egg-info/PKG-INFO
sitrep.egg-info/SOURCES.txt
sitrep.egg-info/dependency_links.txt
sitrep.egg-info/not-zip-safe
sitrep.egg-info/requires.txt
sitrep.egg-info/top_level.txt