Metadata-Version: 1.1
Name: sitrep
Version: 0.9.0
Summary: A console-based snapshot of Linux system resources
Home-page: http://github.com/vonbrownie/sitrep
Author: Daniel Wayne Armstrong
Author-email: daniel@circuidipity.com
License: GPLv2
Platform: linux
Classifier: Development Status :: 4 - Beta
Classifier: Environment :: Console
Classifier: License :: OSI Approved :: GNU General Public License v2 (GPLv2)
Classifier: Operating System :: POSIX :: Linux
Classifier: Programming Language :: Python :: 2.7
Classifier: Topic :: Utilities
